AUTHORS
COPYING
COPYRIGHT
MANIFEST.in
README
setup.py
RestAuth/__init__.py
RestAuth/manage.py
RestAuth.egg-info/PKG-INFO
RestAuth.egg-info/SOURCES.txt
RestAuth.egg-info/dependency_links.txt
RestAuth.egg-info/requires.txt
RestAuth.egg-info/top_level.txt
RestAuth/Groups/__init__.py
RestAuth/Groups/managers.py
RestAuth/Groups/models.py
RestAuth/Groups/querysets.py
RestAuth/Groups/tests.py
RestAuth/Groups/urls.py
RestAuth/Groups/views.py
RestAuth/Groups/cli/__init__.py
RestAuth/Groups/cli/actions.py
RestAuth/Groups/cli/helpers.py
RestAuth/Groups/cli/parsers.py
RestAuth/Groups/migrations/0001_initial.py
RestAuth/Groups/migrations/0002_auto__add_unique_group_name_service.py
RestAuth/Groups/migrations/__init__.py
RestAuth/RestAuth/__init__.py
RestAuth/RestAuth/localsettings.py.example
RestAuth/RestAuth/settings.py
RestAuth/RestAuth/testsettings.py
RestAuth/RestAuth/urls.py
RestAuth/RestAuth/views.py
RestAuth/RestAuth/wsgi.py
RestAuth/Services/__init__.py
RestAuth/Services/backend.py
RestAuth/Services/decorator.py
RestAuth/Services/models.py
RestAuth/Services/tests.py
RestAuth/Services/views.py
RestAuth/Services/cli/__init__.py
RestAuth/Services/cli/actions.py
RestAuth/Services/cli/parsers.py
RestAuth/Services/migrations/0001_initial.py
RestAuth/Services/migrations/0002_add_new_m2m.py
RestAuth/Services/migrations/0003_new_hosts.py
RestAuth/Services/migrations/0004_delete_old_m2m.py
RestAuth/Services/migrations/0005_auto__del_service.py
RestAuth/Services/migrations/0006_fix_foreign_key_constraint.py
RestAuth/Services/migrations/0007_fix_wrong_relation_name.py
RestAuth/Services/migrations/0008_auto__chg_field_serviceaddress_address.py
RestAuth/Services/migrations/__init__.py
RestAuth/Test/__init__.py
RestAuth/Test/models.py
RestAuth/Test/tests.py
RestAuth/Test/urls.py
RestAuth/Test/views.py
RestAuth/Users/__init__.py
RestAuth/Users/models.py
RestAuth/Users/tests.py
RestAuth/Users/urls.py
RestAuth/Users/validators.py
RestAuth/Users/views.py
RestAuth/Users/cli/__init__.py
RestAuth/Users/cli/parsers.py
RestAuth/Users/migrations/0001_initial.py
RestAuth/Users/migrations/0002_auto.py
